otaku_info_bot/OtakuInfoBot.py
otaku_info_bot/OtakuInfoCommandParser.py
otaku_info_bot/__init__.py
otaku_info_bot/db/AnilistEntry.py
otaku_info_bot/db/MangaChapterGuess.py
otaku_info_bot/db/Notification.py
otaku_info_bot/db/__init__.py
otaku_info_bot/db/config.py
otaku_info_bot/fetching/__init__.py
otaku_info_bot/fetching/anilist.py
otaku_info_bot/fetching/anime.py
otaku_info_bot/fetching/ln.py
otaku_info_bot-0.4.0.data/scripts/otaku-info-bot
otaku_info_bot-0.4.0.dist-info/LICENSE
otaku_info_bot-0.4.0.dist-info/METADATA
otaku_info_bot-0.4.0.dist-info/WHEEL
otaku_info_bot-0.4.0.dist-info/top_level.txt
otaku_info_bot-0.4.0.dist-info/RECORD
