Metadata-Version: 2.1
Name: otaku-info-bot
Version: 0.4.0
Summary: An anime episode reminder
Home-page: https://gitlab.namibsun.net/namibsun/python/otaku-info-bot
Author: Hermann Krumrey
Author-email: hermann@krumreyh.com
License: GNU GPL3
Platform: UNKNOWN
Classifier: License :: OSI Approved :: GNU General Public License v3 (GPLv3)
Requires-Dist: typing
Requires-Dist: requests
Requires-Dist: bokkichat
Requires-Dist: kudubot
Requires-Dist: sqlalchemy
Requires-Dist: bs4
Requires-Dist: sentry-sdk
